{
    "timestamp": "2025-07-07T18:07:22.852388",
    "filename": "chunk_072_20240422.md",
    "raw_entities": "\n\n{\n  \"chunk_id\": \"2024-04-22\",\n  \"entities\": [\n    {\"name\": \"WGS\", \"type\": \"生物技术\"},\n    {\"name\": \"Microreact\", \"type\": \"生物信息工具\"},\n    {\"name\": \"Pathogenwatch\", \"type\": \"生物信息工具\"},\n    {\"name\": \"AMR\", \"type\": \"生物分子\"},\n    {\"name\": \"MGE\", \"type\": \"生物分子\"},\n    {\"name\": \"抗生素耐药性\", \"type\": \"生物医学概念\"},\n    {\"name\": \"遗传相关性\", \"type\": \"其他\"},\n    {\"name\": \"传播\", \"type\": \"其他\"},\n    {\"name\": \"高风险克隆\", \"type\": \"其他\"},\n    {\"name\": \"基因组监测\", \"type\": \"项目活动\"},\n    {\"name\": \"实验室\", \"type\": \"其他\"},\n    {\"name\": \"文献阅读\", \"type\": \"项目活动\"}\n  ]\n}",
    "raw_relations": "\n\n{\n  \"chunk_id\": \"2024-04-22\",\n  \"relations\": [\n    {\"head\": \"细菌分离株\", \"type\": \"使用\", \"tail\": \"WGS\"},\n    {\"head\": \"WGS\", \"type\": \"使用\", \"tail\": \"Microreact\"},\n    {\"head\": \"WGS\", \"type\": \"使用\", \"tail\": \"Pathogenwatch\"},\n    {\"head\": \"遗传相关性\", \"type\": \"属于\", \"tail\": \"细菌分离株\"},\n    {\"head\": \"AMR\", \"type\": \"属于\", \"tail\": \"细菌分离株\"},\n    {\"head\": \"MGE\", \"type\": \"属于\", \"tail\": \"细菌分离株\"},\n    {\"head\": \"传播\", \"type\": \"调控\", \"tail\": \"高风险克隆\"},\n    {\"head\": \"实验室\", \"type\": \"整合\", \"tail\": \"基因组监测\"},\n    {\"head\": \"WGS\", \"type\": \"属于\", \"tail\": \"文献阅读\"}\n  ]\n}"
}