{
    "timestamp": "2025-07-07T18:07:10.354631",
    "filename": "chunk_079_unknown_date.md",
    "raw_entities": "\n\n```json\n{\n  \"chunk_id\": \"2024-03-02\",\n  \"entities\": [\n    {\"name\": \"抗菌素耐药基因\", \"type\": \"生物分子\"},\n    {\"name\": \"全基因组测序\", \"type\": \"生物技术\"},\n    {\"name\": \"聚合酶链反应\", \"type\": \"生物技术\"},\n    {\"name\": \"深度神经网络\", \"type\": \"深度学习概念\"},\n    {\"name\": \"深度学习\", \"type\": \"深度学习概念\"},\n    {\"name\": \"DeepARG-SS\", \"type\": \"生物信息工具\"},\n    {\"name\": \"DeepARG-LS\", \"type\": \"生物信息工具\"},\n    {\"name\": \"抗微生物药物耐药性\", \"type\": \"生物医学概念\"},\n    {\"name\": \"耐药表型\", \"type\": \"生物医学概念\"},\n    {\"name\": \"功能宏基因组学\", \"type\": \"生物技术\"},\n    {\"name\": \"抗菌素耐药性\", \"type\": \"生物医学概念\"},\n    {\"name\": \"抗菌管理\", \"type\": \"项目活动\"},\n    {\"name\": \"数据库\", \"type\": \"生物信息工具\"},\n    {\"name\": \"模型\", \"type\": \"深度学习概念\"},\n    {\"name\": \"公共卫生危机\", \"type\": \"生物医学概念\"},\n    {\"name\": \"抗菌素敏感性\", \"type\": \"生物医学概念\"},\n    {\"name\": \"精度\", \"type\": \"深度学习概念\"},\n    {\"name\": \"召回率\", \"type\": \"深度学习概念\"},\n    {\"name\": \"短读长序列\", \"type\": \"生物分子\"},\n    {\"name\": \"全基因长度序列\", \"type\": \"生物分子\"},\n    {\"name\": \"基因组背景\", \"type\": \"生物分子\"},\n    {\"name\": \"宿主细菌种类\", \"type\": \"生物分子\"},\n    {\"name\": \"地理位置\", \"type\": \"其他\"}\n  ]\n}\n```",
    "raw_relations": "\n\n```json\n{\n  \"chunk_id\": \"2024-03-02\",\n  \"relations\": [\n    {\"head\": \"全基因组测序\", \"type\": \"使用\", \"tail\": \"抗菌素耐药基因\"},\n    {\"head\": \"全基因组测序\", \"type\": \"因果\", \"tail\": \"抗菌素耐药性\"},\n    {\"head\": \"全基因组测序\", \"type\": \"因果\", \"tail\": \"抗菌素敏感性\"},\n    {\"head\": \"全基因组测序\", \"type\": \"因果\", \"tail\": \"耐药表型\"},\n    {\"head\": \"聚合酶链反应\", \"type\": \"因果\", \"tail\": \"耐药表型\"},\n    {\"head\": \"全基因组测序\", \"type\": \"优于\", \"tail\": \"聚合酶链反应\"},\n    {\"head\": \"深度神经网络\", \"type\": \"使用\", \"tail\": \"深度学习\"},\n    {\"head\": \"深度神经网络\", \"type\": \"使用\", \"tail\": \"抗菌素耐药基因\"},\n    {\"head\": \"深度神经网络\", \"type\": \"使用\", \"tail\": \"抗菌活性\"},\n    {\"head\": \"深度学习\", \"type\": \"使用\", \"tail\": \"抗菌素耐药基因\"},\n    {\"head\": \"深度学习\", \"type\": \"属于\", \"tail\": \"模型\"},\n    {\"head\": \"DeepARG-SS\", \"type\": \"使用\", \"tail\": \"短读长序列\"},\n    {\"head\": \"DeepARG-LS\", \"type\": \"使用\", \"tail\": \"全基因长度序列\"},\n    {\"head\": \"DeepARG-SS\", \"type\": \"使用\", \"tail\": \"深度学习\"},\n    {\"head\": \"DeepARG-LS\", \"type\": \"使用\", \"tail\": \"深度学习\"},\n    {\"head\": \"DeepARG-SS\", \"type\": \"因果\", \"tail\": \"抗菌素耐药基因\"},\n    {\"head\": \"DeepARG-LS\", \"type\": \"因果\", \"tail\": \"抗菌素耐药基因\"},\n    {\"head\": \"抗菌素耐药性\", \"type\": \"属于\", \"tail\": \"抗微生物药物耐药性\"},\n    {\"head\": \"抗菌素耐药性\", \"type\": \"导致\", \"tail\": \"公共卫生危机\"},\n    {\"head\": \"抗菌素耐药性\", \"type\": \"因果\", \"tail\": \"抗菌管理\"},\n    {\"head\": \"抗菌管理\", \"type\": \"属于\", \"tail\": \"项目活动\"},\n    {\"head\": \"模型\", \"type\": \"使用\", \"tail\": \"精度\"},\n    {\"head\": \"模型\", \"type\": \"使用\", \"tail\": \"召回率\"},\n    {\"head\": \"抗菌素耐药基因\", \"type\": \"属于\", \"tail\": \"数据库\"},\n    {\"head\": \"模型\", \"type\": \"属于\", \"tail\": \"生物信息工具\"},\n    {\"head\": \"功能宏基因组学\", \"type\": \"使用\", \"tail\": \"抗菌素耐药基因\"},\n    {\"head\": \"功能宏基因组学\", \"type\": \"属于\", \"tail\": \"生物技术\"},\n    {\"head\": \"抗菌素耐药基因\", \"type\": \"属于\", \"tail\": \"生物分子\"},\n    {\"head\": \"模型\", \"type\": \"需要\", \"tail\": \"基因组背景\"},\n    {\"head\": \"模型\", \"type\": \"需要\", \"tail\": \"宿主细菌种类\"},\n    {\"head\": \"模型\", \"type\": \"需要\", \"tail\": \"地理位置\"}\n  ]\n}\n```"
}