{
    "timestamp": "2025-07-07T17:13:38.260989",
    "filename": "chunk_063_20230817.md",
    "entities": {
        "chunk_id": "2024-03-02",
        "entities": [
            {
                "name": "torch.bmm()",
                "type": "生物信息工具"
            },
            {
                "name": "permute()",
                "type": "生物信息工具"
            },
            {
                "name": "Multi-Head-Attention",
                "type": "深度学习概念"
            },
            {
                "name": "self-Attention",
                "type": "深度学习概念"
            },
            {
                "name": "DataLoader",
                "type": "生物信息工具"
            },
            {
                "name": "Dataset",
                "type": "生物信息工具"
            },
            {
                "name": "random_split()",
                "type": "生物信息工具"
            },
            {
                "name": "dropout",
                "type": "深度学习概念"
            },
            {
                "name": "model.eval()",
                "type": "生物信息工具"
            },
            {
                "name": "softmax",
                "type": "深度学习概念"
            },
            {
                "name": "crossentropy",
                "type": "深度学习概念"
            },
            {
                "name": "TorchProtein",
                "type": "生物信息工具"
            }
        ]
    },
    "relations": {
        "chunk_id": "2024-03-02",
        "relations": [
            {
                "head": "数据加载",
                "type": "使用",
                "tail": "DataLoader"
            },
            {
                "head": "数据加载",
                "type": "使用",
                "tail": "Dataset"
            },
            {
                "head": "数据加载",
                "type": "使用",
                "tail": "random_split()"
            },
            {
                "head": "Multi-Head-Attention",
                "type": "属于",
                "tail": "self-Attention"
            },
            {
                "head": "神经网络",
                "type": "使用",
                "tail": "dropout"
            },
            {
                "head": "模型预测",
                "type": "使用",
                "tail": "model.eval()"
            },
            {
                "head": "深度学习模型",
                "type": "使用",
                "tail": "softmax"
            },
            {
                "head": "分类任务",
                "type": "使用",
                "tail": "crossentropy"
            },
            {
                "head": "crossentropy",
                "type": "包含",
                "tail": "softmax"
            },
            {
                "head": "TorchProtein",
                "type": "属于",
                "tail": "深度学习概念"
            }
        ]
    },
    "status": "success"
}